{"type":"FeatureCollection","features":[{"type":"Feature","id":"hastaneler.1","geometry":{"type":"Point","coordinates":[32.90865363,39.92005538,0]},"geometry_name":"geom","properties":{"name":"Özel Natomed Hastanesi","descriptio":"Tuzluçayır Mah, Natoyolu Caddesı No:49, 06620 Mamak/Ankara","timestamp":null,"begin":null,"end":null,"altitudemo":null,"tessellate":-1,"extrude":0,"visibility":-1,"draworder":null,"icon":null}},{"type":"Feature","id":"hastaneler.2","geometry":{"type":"Point","coordinates":[32.8853329,39.93410556,0]},"geometry_name":"geom","properties":{"name":"Cebeci Hastanesi","descriptio":"Balkiraz, AÜ Tıp Fakültesi Hst., 06620 Mamak/Ankara","timestamp":null,"begin":null,"end":null,"altitudemo":null,"tessellate":-1,"extrude":0,"visibility":-1,"draworder":null,"icon":null}}],"totalFeatures":2,"numberMatched":2,"numberReturned":2,"timeStamp":"2021-04-10T20:35:28.670Z","crs":{"type":"name","properties":{"name":"urn:ogc:def:crs:EPSG::4326"}}}